aind_slims_service_client/__init__.py
aind_slims_service_client/api_client.py
aind_slims_service_client/api_response.py
aind_slims_service_client/configuration.py
aind_slims_service_client/exceptions.py
aind_slims_service_client/py.typed
aind_slims_service_client/rest.py
aind_slims_service_client/api/__init__.py
aind_slims_service_client/api/default_api.py
aind_slims_service_client/api/healthcheck_api.py
aind_slims_service_client/models/__init__.py
aind_slims_service_client/models/ecephys_reward_spouts.py
aind_slims_service_client/models/ecephys_stream_module.py
aind_slims_service_client/models/health_check.py
aind_slims_service_client/models/histology_reagent_data.py
aind_slims_service_client/models/histology_wash_data.py
aind_slims_service_client/models/http_validation_error.py
aind_slims_service_client/models/slims_ecephys_data.py
aind_slims_service_client/models/slims_histology_data.py
aind_slims_service_client/models/slims_spim_data.py
aind_slims_service_client/models/slims_viral_injection_data.py
aind_slims_service_client/models/slims_viral_material_data.py
aind_slims_service_client/models/slims_water_restriction_data.py
aind_slims_service_client/models/validation_error.py
aind_slims_service_client/models/validation_error_loc_inner.py
aind_slims_service_client-0.3.2.dist-info/METADATA
aind_slims_service_client-0.3.2.dist-info/WHEEL
aind_slims_service_client-0.3.2.dist-info/top_level.txt
aind_slims_service_client-0.3.2.dist-info/RECORD
